py_desc/__init__.py
py_desc/base.py
py_desc/built_in/__init__.py
py_desc/built_in/bool.py
py_desc/built_in/dict.py
py_desc/built_in/float.py
py_desc/built_in/integer.py
py_desc/built_in/list.py
py_desc/built_in/set.py
py_desc/built_in/string.py
py_desc/built_in/tuple.py
py_desc-0.5.2.dist-info/LICENSE
py_desc-0.5.2.dist-info/METADATA
py_desc-0.5.2.dist-info/WHEEL
py_desc-0.5.2.dist-info/top_level.txt
py_desc-0.5.2.dist-info/RECORD
