Metadata-Version: 2.1
Name: py-desc
Version: 0.5.2
Summary: A simple fields descriptors tool
Home-page: https://github.com/syth0le/py_desc
Author: Cherednichenko Daniil
Author-email: syth0le565@gmail.com
License: Apache 2.0
Platform: all
Classifier: Operating System :: OS Independent
Classifier: License :: OSI Approved :: Apache Software License
Classifier: Programming Language :: Python :: 3
Classifier: Programming Language :: Python :: 3.7
Classifier: Programming Language :: Python :: 3.8
Classifier: Programming Language :: Python :: 3.9
Classifier: Programming Language :: Python :: 3.10
Classifier: Topic :: Software Development :: Libraries
Requires-Python: >=3.7.0
License-File: LICENSE
